foliant/preprocessors/checksources.py
foliantcontrib_checksources-1.0.6.dist-info/licenses/LICENSE
foliantcontrib_checksources-1.0.6.dist-info/METADATA
foliantcontrib_checksources-1.0.6.dist-info/WHEEL
foliantcontrib_checksources-1.0.6.dist-info/top_level.txt
foliantcontrib_checksources-1.0.6.dist-info/RECORD
