Metadata-Version: 2.4
Name: foliantcontrib.checksources
Version: 1.0.6
Summary: Foliant preprocessor that checks the project for missing and unmentioned files.
Home-page: https://github.com/foliant-docs/foliantcontrib.checksources
Author: foliant-docs
Author-email: foliant-shared@yandex.ru
License: MIT
Platform: any
Classifier: Development Status :: 5 - Production/Stable
Classifier: Environment :: Console
Classifier: Intended Audience :: Developers
Classifier: License :: OSI Approved :: MIT License
Classifier: Operating System :: OS Independent
Classifier: Programming Language :: Python
Classifier: Topic :: Documentation
Classifier: Topic :: Utilities
License-File: LICENSE
Requires-Dist: foliant>=1.0.8
Requires-Dist: foliantcontrib.utils>=1.0.3
Dynamic: author
Dynamic: author-email
Dynamic: classifier
Dynamic: description
Dynamic: description-content-type
Dynamic: home-page
Dynamic: license
Dynamic: license-file
Dynamic: platform
Dynamic: requires-dist
Dynamic: summary
